kox/__init__.py
kox/cli.py
kox/client.py
kox-1.0.0.dist-info/METADATA
kox-1.0.0.dist-info/WHEEL
kox-1.0.0.dist-info/entry_points.txt
kox-1.0.0.dist-info/top_level.txt
kox-1.0.0.dist-info/RECORD
