Metadata-Version: 2.1
Name: kox
Version: 1.0.0
Summary: Kox - A simple code management tool for version control
Home-page: https://github.com/decrule/kox
Author: Kox Team
Author-email: 
Project-URL: Bug Reports, https://github.com/decrule/kox/issues
Project-URL: Source, https://github.com/decrule/kox
Project-URL: Documentation, https://github.com/decrule/kox#readme
Keywords: version-control,code-management,git-alternative,code-versioning
Classifier: Development Status :: 4 - Beta
Classifier: Intended Audience :: Developers
Classifier: Topic :: Software Development :: Version Control
Classifier: License :: OSI Approved :: MIT License
Classifier: Programming Language :: Python :: 3
Classifier: Programming Language :: Python :: 3.7
Classifier: Programming Language :: Python :: 3.8
Classifier: Programming Language :: Python :: 3.9
Classifier: Programming Language :: Python :: 3.10
Classifier: Programming Language :: Python :: 3.11
Classifier: Programming Language :: Python :: 3.12
Classifier: Programming Language :: Python :: 3.13
Requires-Python: >=3.7
Requires-Dist: requests>=2.31.0
Requires-Dist: tqdm>=4.66.0
Requires-Dist: click>=8.0.0
